backgroundremover/__init__.py
backgroundremover/bg.py
backgroundremover/github.py
backgroundremover/utilities.py
backgroundremover/cmd/__init__.py
backgroundremover/cmd/cli.py
backgroundremover/cmd/server.py
backgroundremover/u2net/__init__.py
backgroundremover/u2net/data_loader.py
backgroundremover/u2net/detect.py
backgroundremover/u2net/u2net.py
backgroundremover-0.3.8.dist-info/licenses/LICENSE.txt
backgroundremover-0.3.8.dist-info/METADATA
backgroundremover-0.3.8.dist-info/WHEEL
backgroundremover-0.3.8.dist-info/entry_points.txt
backgroundremover-0.3.8.dist-info/top_level.txt
backgroundremover-0.3.8.dist-info/RECORD
