Metadata-Version: 2.4
Name: backgroundremover
Version: 0.3.8
Summary: Background remover from image and video using AI
Home-page: https://github.com/nadermx/backgroundremover
Author: Johnathan Nader
Author-email: john@nader.mx
License: MIT
Keywords: remove,background,u2net,remove background,background remover
Classifier: Programming Language :: Python :: 3 :: Only
Requires-Python: >=3.6, <4
License-File: LICENSE.txt
Requires-Dist: certifi
Requires-Dist: charset-normalizer
Requires-Dist: filelock
Requires-Dist: idna
Requires-Dist: PySocks
Requires-Dist: six
Requires-Dist: urllib3
Requires-Dist: numpy
Requires-Dist: scikit-image
Requires-Dist: torch>=1.13.0
Requires-Dist: torchvision>=0.14.0
Requires-Dist: waitress
Requires-Dist: tqdm
Requires-Dist: requests
Requires-Dist: scipy
Requires-Dist: pymatting
Requires-Dist: filetype
Requires-Dist: hsh
Requires-Dist: more_itertools
Requires-Dist: moviepy>=2.0.0
Requires-Dist: Pillow
Requires-Dist: pillow-heif
Requires-Dist: ffmpeg-python
Requires-Dist: flask
Dynamic: author
Dynamic: author-email
Dynamic: classifier
Dynamic: description
Dynamic: description-content-type
Dynamic: home-page
Dynamic: keywords
Dynamic: license
Dynamic: license-file
Dynamic: requires-dist
Dynamic: requires-python
Dynamic: summary
